scikit_learn_tree.libs/libgomp-a34b3233.so.1.0.0
sklearn_fork/isotonic.py
sklearn_fork/conftest.py
sklearn_fork/dummy.py
sklearn_fork/_isotonic.cpython-310-x86_64-linux-gnu.so
sklearn_fork/exceptions.py
sklearn_fork/discriminant_analysis.py
sklearn_fork/naive_bayes.py
sklearn_fork/_config.py
sklearn_fork/_min_dependencies.py
sklearn_fork/random_projection.py
sklearn_fork/__init__.py
sklearn_fork/_distributor_init.py
sklearn_fork/multiclass.py
sklearn_fork/calibration.py
sklearn_fork/pipeline.py
sklearn_fork/kernel_ridge.py
sklearn_fork/base.py
sklearn_fork/kernel_approximation.py
sklearn_fork/multioutput.py
sklearn_fork/metrics/_regression.py
sklearn_fork/metrics/_ranking.py
sklearn_fork/metrics/_classification.py
sklearn_fork/metrics/__init__.py
sklearn_fork/metrics/_scorer.py
sklearn_fork/metrics/pairwise.py
sklearn_fork/metrics/_pairwise_fast.cpython-310-x86_64-linux-gnu.so
sklearn_fork/metrics/_dist_metrics.cpython-310-x86_64-linux-gnu.so
sklearn_fork/metrics/_base.py
sklearn_fork/metrics/_dist_metrics.pxd
sklearn_fork/metrics/cluster/_bicluster.py
sklearn_fork/metrics/cluster/_expected_mutual_info_fast.cpython-310-x86_64-linux-gnu.so
sklearn_fork/metrics/cluster/__init__.py
sklearn_fork/metrics/cluster/_unsupervised.py
sklearn_fork/metrics/cluster/_supervised.py
sklearn_fork/metrics/cluster/tests/test_unsupervised.py
sklearn_fork/metrics/cluster/tests/test_supervised.py
sklearn_fork/metrics/cluster/tests/__init__.py
sklearn_fork/metrics/cluster/tests/test_bicluster.py
sklearn_fork/metrics/cluster/tests/test_common.py
sklearn_fork/metrics/_plot/roc_curve.py
sklearn_fork/metrics/_plot/det_curve.py
sklearn_fork/metrics/_plot/confusion_matrix.py
sklearn_fork/metrics/_plot/regression.py
sklearn_fork/metrics/_plot/__init__.py
sklearn_fork/metrics/_plot/precision_recall_curve.py
sklearn_fork/metrics/_plot/tests/test_common_curve_display.py
sklearn_fork/metrics/_plot/tests/test_precision_recall_display.py
scikit_learn_tree-1.2.3.dist-info/WHEEL
scikit_learn_tree-1.2.3.dist-info/COPYING
scikit_learn_tree-1.2.3.dist-info/top_level.txt
scikit_learn_tree-1.2.3.dist-info/RECORD
scikit_learn_tree-1.2.3.dist-info/METADATA
