Metadata-Version: 2.1
Name: scikit-learn-tree
Version: 1.2.3
Summary: A maintained fork of scikit-learn that extends the tree submodule.
Home-page: http://scikit-learn.org
Download-URL: https://pypi.org/project/scikit-learn-tree/#files
Maintainer: Adam Li
Maintainer-email: adam.li@columbia.edu
License: new BSD
Project-URL: Bug Tracker, https://github.com/neurodata/scikit-learn/issues
Project-URL: Documentation, https://scikit-learn.org/stable/documentation.html
Project-URL: Source Code, https://github.com/neurodata/scikit-learn
Classifier: Intended Audience :: Science/Research
Classifier: Intended Audience :: Developers
Classifier: License :: OSI Approved :: BSD License
Classifier: Programming Language :: C
Classifier: Programming Language :: Python
Classifier: Topic :: Software Development
Classifier: Topic :: Scientific/Engineering
Classifier: Development Status :: 5 - Production/Stable
Classifier: Operating System :: Microsoft :: Windows
Classifier: Operating System :: POSIX
Classifier: Operating System :: Unix
Classifier: Operating System :: MacOS
Classifier: Programming Language :: Python :: 3
Classifier: Programming Language :: Python :: 3.8
Classifier: Programming Language :: Python :: 3.9
Classifier: Programming Language :: Python :: 3.10
Classifier: Programming Language :: Python :: 3.11
Classifier: Programming Language :: Python :: Implementation :: CPython
Classifier: Programming Language :: Python :: Implementation :: PyPy
Requires-Python: >=3.8
License-File: COPYING
Requires-Dist: numpy (>=1.17.3)
Requires-Dist: scipy (>=1.5.0)
Requires-Dist: joblib (>=1.1.1)
Requires-Dist: threadpoolctl (>=2.0.0)
Provides-Extra: benchmark
Requires-Dist: matplotlib (>=3.1.3) ; extra == 'benchmark'
Requires-Dist: pandas (>=1.0.5) ; extra == 'benchmark'
Requires-Dist: memory-profiler (>=0.57.0) ; extra == 'benchmark'
Provides-Extra: docs
Requires-Dist: matplotlib (>=3.1.3) ; extra == 'docs'
Requires-Dist: scikit-image (>=0.16.2) ; extra == 'docs'
Requires-Dist: pandas (>=1.0.5) ; extra == 'docs'
Requires-Dist: seaborn (>=0.9.0) ; extra == 'docs'
Requires-Dist: memory-profiler (>=0.57.0) ; extra == 'docs'
Requires-Dist: sphinx (>=4.0.1) ; extra == 'docs'
Requires-Dist: sphinx-gallery (>=0.7.0) ; extra == 'docs'
Requires-Dist: numpydoc (>=1.2.0) ; extra == 'docs'
Requires-Dist: Pillow (>=7.1.2) ; extra == 'docs'
Requires-Dist: pooch (>=1.6.0) ; extra == 'docs'
Requires-Dist: sphinx-prompt (>=1.3.0) ; extra == 'docs'
Requires-Dist: sphinxext-opengraph (>=0.4.2) ; extra == 'docs'
Requires-Dist: plotly (>=5.10.0) ; extra == 'docs'
Provides-Extra: examples
Requires-Dist: matplotlib (>=3.1.3) ; extra == 'examples'
Requires-Dist: scikit-image (>=0.16.2) ; extra == 'examples'
Requires-Dist: pandas (>=1.0.5) ; extra == 'examples'
Requires-Dist: seaborn (>=0.9.0) ; extra == 'examples'
Requires-Dist: pooch (>=1.6.0) ; extra == 'examples'
Requires-Dist: plotly (>=5.10.0) ; extra == 'examples'
Provides-Extra: tests
Requires-Dist: matplotlib (>=3.1.3) ; extra == 'tests'
Requires-Dist: scikit-image (>=0.16.2) ; extra == 'tests'
Requires-Dist: pandas (>=1.0.5) ; extra == 'tests'
Requires-Dist: pytest (>=5.3.1) ; extra == 'tests'
Requires-Dist: pytest-cov (>=2.9.0) ; extra == 'tests'
Requires-Dist: flake8 (>=3.8.2) ; extra == 'tests'
Requires-Dist: black (>=23.3.0) ; extra == 'tests'
Requires-Dist: mypy (>=0.961) ; extra == 'tests'
Requires-Dist: pyamg (>=4.0.0) ; extra == 'tests'
Requires-Dist: numpydoc (>=1.2.0) ; extra == 'tests'
Requires-Dist: pooch (>=1.6.0) ; extra == 'tests'
